export_yaml/__init__.py
export_yaml-0.0.2.data/scripts/export_yaml
export_yaml-0.0.2.dist-info/LICENSE
export_yaml-0.0.2.dist-info/METADATA
export_yaml-0.0.2.dist-info/WHEEL
export_yaml-0.0.2.dist-info/top_level.txt
export_yaml-0.0.2.dist-info/RECORD
