Metadata-Version: 2.1
Name: export-yaml
Version: 0.0.2
Summary: Export environment variable from YAML file
Home-page: https://github.com/danggrianto/export_yaml/
Author: Daniel Anggrianto
Author-email: d.anggrianto@gmail.com
License: UNKNOWN
Platform: UNKNOWN
Classifier: Programming Language :: Python
Classifier: License :: OSI Approved :: MIT License
Classifier: Operating System :: OS Independent
Requires-Dist: pyyaml
